linkedin_messaging/__init__.py
linkedin_messaging/api_objects.py
linkedin_messaging/exceptions.py
linkedin_messaging/linkedin.py
linkedin_messaging/py.typed
linkedin_messaging-0.6.0.dist-info/LICENSE
linkedin_messaging-0.6.0.dist-info/WHEEL
linkedin_messaging-0.6.0.dist-info/METADATA
linkedin_messaging-0.6.0.dist-info/RECORD
